tei_reader/__init__.py
tei_reader/tei_reader.py
tei_reader/models/__init__.py
tei_reader/models/attribute.py
tei_reader/models/corpora.py
tei_reader/models/division.py
tei_reader/models/document.py
tei_reader/models/element.py
tei_reader/models/part.py
tei_reader/models/placeholder_attribute.py
tei_reader/models/placeholder_division.py
tei_reader/models/placeholder_element.py
tei_reader/models/placeholder_part.py
tei_reader/transform/tei-content.dtd
tei_reader/transform/tei-transform.xsl
tei_reader_3.5-0.1.6.dist-info/METADATA
tei_reader_3.5-0.1.6.dist-info/RECORD
tei_reader_3.5-0.1.6.dist-info/WHEEL
tei_reader_3.5-0.1.6.dist-info/top_level.txt
